lamb_engine/__init__.py
lamb_engine/__main__.py
lamb_engine/parser.py
lamb_engine/utils.py
lamb_engine/nodes/__init__.py
lamb_engine/nodes/functions.py
lamb_engine/nodes/misc.py
lamb_engine/nodes/nodes.py
lamb_engine/runner/__init__.py
lamb_engine/runner/commands.py
lamb_engine/runner/misc.py
lamb_engine/runner/runner.py
lamb_engine-1.1.9.dist-info/LICENSE
lamb_engine-1.1.9.dist-info/METADATA
lamb_engine-1.1.9.dist-info/WHEEL
lamb_engine-1.1.9.dist-info/entry_points.txt
lamb_engine-1.1.9.dist-info/top_level.txt
lamb_engine-1.1.9.dist-info/RECORD
