Metadata-Version: 2.1
Name: lamb-engine
Version: 1.1.9
Summary: A lambda calculus engine
Author-email: Mark <mark@betalupi.com>
License: GNU General Public License v3 (GPLv3)
Project-URL: Homepage, https://git.betalupi.com/Mark/lamb
Classifier: Programming Language :: Python :: 3
Classifier: License :: OSI Approved :: GNU General Public License v3 (GPLv3)
Classifier: Operating System :: OS Independent
Classifier: Environment :: Console
Requires-Python: >=3.7
License-File: LICENSE
Requires-Dist: prompt-toolkit (==3.0.31)
Requires-Dist: pyparsing (==3.0.9)
